ipychart/__init__.py
ipychart/_version.py
ipychart/chart.py
ipychart/plots.py
ipychart/labextension/package.json
ipychart/labextension/static/122.7e9a56692d8d107dae67.js
ipychart/labextension/static/285.4d5babae3980cf84c119.js
ipychart/labextension/static/285.4d5babae3980cf84c119.js.LICENSE.txt
ipychart/labextension/static/286.4a8282f5dc6b95c3126a.js
ipychart/labextension/static/286.4a8282f5dc6b95c3126a.js.LICENSE.txt
ipychart/labextension/static/29.d598449b96de5da0e9b0.js
ipychart/labextension/static/29.d598449b96de5da0e9b0.js.LICENSE.txt
ipychart/labextension/static/358.2cf63e600d9567ca35c0.js
ipychart/labextension/static/509.55f2378fe5dd1e3b4fe6.js
ipychart/labextension/static/543.e9d4943b1739ef1327e8.js
ipychart/labextension/static/543.e9d4943b1739ef1327e8.js.LICENSE.txt
ipychart/labextension/static/584.85742ce63d94e9dbffce.js
ipychart/labextension/static/787.a2ea7963e549e157dedf.js
ipychart/labextension/static/839.76257a91f0cd588961fe.js
ipychart/labextension/static/839.76257a91f0cd588961fe.js.LICENSE.txt
ipychart/labextension/static/929.fbcbc1a27ce96a06a7c5.js
ipychart/labextension/static/929.fbcbc1a27ce96a06a7c5.js.LICENSE.txt
ipychart/labextension/static/remoteEntry.a93b9157c1443fafeade.js
ipychart/labextension/static/style.js
ipychart/labextension/static/third-party-licenses.json
ipychart/nbextension/index.js
ipychart/nbextension/index.js.LICENSE.txt
ipychart/nbextension/index.js.map
ipychart/utils/__init__.py
ipychart/utils/constants.py
ipychart/utils/exceptions.py
ipychart/utils/messages.py
ipychart/utils/plots_utils.py
ipychart-0.5.2.data/data/share/jupyter/labextensions/ipychart/package.json
ipychart-0.5.2.data/data/share/jupyter/labextensions/ipychart/static/122.7e9a56692d8d107dae67.js
ipychart-0.5.2.data/data/share/jupyter/labextensions/ipychart/static/285.4d5babae3980cf84c119.js
ipychart-0.5.2.data/data/share/jupyter/labextensions/ipychart/static/285.4d5babae3980cf84c119.js.LICENSE.txt
ipychart-0.5.2.dist-info/METADATA
ipychart-0.5.2.dist-info/WHEEL
ipychart-0.5.2.dist-info/licenses/LICENSE
ipychart-0.5.2.dist-info/RECORD
