Metadata-Version: 2.3
Name: ipychart
Version: 0.5.2
Summary: A Jupyter - Chart.js bridge enabling interactive data visualization with Python.
Project-URL: Homepage, https://github.com/nicohlr/ipychart
Author-email: Nicolas Houlier <nicolas.houlier@gmail.com>
License: Copyright (c) 2020 Nicolas Houlier
License-File: LICENSE
Keywords: IPython,Jupyter,Widgets
Classifier: Framework :: Jupyter
Classifier: Intended Audience :: Developers
Classifier: Intended Audience :: Science/Research
Classifier: License :: OSI Approved :: BSD License
Classifier: Programming Language :: Python
Classifier: Programming Language :: Python :: 3
Classifier: Programming Language :: Python :: 3.7
Classifier: Programming Language :: Python :: 3.8
Classifier: Programming Language :: Python :: 3.9
Classifier: Programming Language :: Python :: 3.10
Classifier: Programming Language :: Python :: 3.11
Classifier: Programming Language :: Python :: 3.12
Requires-Python: >=3.10
Requires-Dist: ipywidgets>=8.0.0
Requires-Dist: numpy>=1.18.0
Requires-Dist: pandas>=1.0.3
Requires-Dist: pydash>=4.8.0
Requires-Dist: scikit-learn>=0.23.2
Provides-Extra: examples
Provides-Extra: test
Requires-Dist: nbval; extra == 'test'
Requires-Dist: pytest-cov; extra == 'test'
Requires-Dist: pytest>=6.0; extra == 'test'
